scignumpy/__init__.py
scignumpy/array.py
scignumpy/linalg.py
scignumpy/math_functions.py
scignumpy/matrix.py
scignumpy/utils.py
scignumpy-0.1.3.dist-info/LICENSE
scignumpy-0.1.3.dist-info/METADATA
scignumpy-0.1.3.dist-info/WHEEL
scignumpy-0.1.3.dist-info/top_level.txt
scignumpy-0.1.3.dist-info/RECORD
