Metadata-Version: 2.2
Name: scignumpy
Version: 0.1.3
Summary: A lightweight numerical computation library inspired by NumPy.
Home-page: https://github.com/Sumedh1599/scignumpy
Author: Sumedh Patil
Author-email: admin@aipresso.uk
Classifier: Programming Language :: Python :: 3
Classifier: License :: OSI Approved :: MIT License
Classifier: Operating System :: OS Independent
Requires-Python: >=3.6
License-File: LICENSE
Requires-Dist: numpy
Dynamic: author
Dynamic: author-email
Dynamic: classifier
Dynamic: description
Dynamic: description-content-type
Dynamic: home-page
Dynamic: requires-dist
Dynamic: requires-python
Dynamic: summary
